itacovidlib
tests
