Metadata-Version: 1.1
Name: itacovidlib
Version: 0.1.3
Summary: Python library for COVID-19 infections and vaccinations in Italy data retrieval and analysis
Home-page: https://github.com/FedericoCorchia/Italian_COVID_Library
Author: Federico Corchia
Author-email: UNKNOWN
License: MIT
Download-URL: https://github.com/FedericoCorchia/itacovidlib/archive/refs/tags/v0.1.3-alpha.tar.gz
Keywords: COVID-19 infection vaccination Italy
Platform: UNKNOWN
Classifier: Development Status :: 3 - Alpha
Classifier: Topic :: Utilities
Classifier: License :: OSI Approved :: MIT License
